<clickhouse>
    <remote_servers>
        <main_cluster>
            <shard>
                <replica>
                    <default_database from_env="CH_DB_NAME" />
                    <host>clickhouse-node1</host>
                    <port>9000</port>
                    <user from_env='CH_USER' />
                    <password from_env='CH_PASSWORD' />
                </replica>
                <replica>
                    <default_database from_env="CH_REPLICA_DB_NAME" />
                    <host>clickhouse-node2</host>
                    <port>9000</port>
                    <user from_env='CH_USER' />
                    <password from_env='CH_PASSWORD' />
                </replica>
            </shard>
            <shard>
                <replica>
                    <default_database from_env="CH_DB_NAME" />
                    <host>clickhouse-node3</host>
                    <port>9000</port>
                    <user from_env='CH_USER' />
                    <password from_env='CH_PASSWORD' />
                </replica>
                <replica>
                    <default_database from_env="CH_REPLICA_DB_NAME" />
                    <host>clickhouse-node4</host>
                    <port>9000</port>
                    <user from_env='CH_USER' />
                    <password from_env='CH_PASSWORD' />
                </replica>
            </shard>
        </main_cluster>
    </remote_servers>
</clickhouse>
